README.md
setup.py
lianwu/__init__.py
lianwu/lianwu.py
lianwu.egg-info/PKG-INFO
lianwu.egg-info/SOURCES.txt
lianwu.egg-info/dependency_links.txt
lianwu.egg-info/top_level.txt