Metadata-Version: 2.1
Name: lianwu
Version: 0.0.1
Summary: wo shi ni ba ba
Home-page: https://github.com/Myxianer
Author: lianwu
Author-email: oushijianhun@126.com
License: UNKNOWN
Platform: UNKNOWN
Classifier: Programming Language :: Python :: 3
Classifier: License :: OSI Approved :: MIT License
Classifier: Operating System :: OS Independent
